slack_wrapper
