Metadata-Version: 1.1
Name: slack-wrapper
Version: 0.4.2.2
Summary: A wrapper for the slack API and RTM
Home-page: https://github.com/therightmandev/slack-wrapper
Author: therightman
Author-email: therightmandev@gmail.com
License: MIT
Download-URL: https://github.com/therightmandev/slack-wrapper/tarball/0.4.2.2
Keywords: slack,api,bot,bots
Platform: UNKNOWN
